{"pk": 6067, "wordlist_pk": 6067, "code_wals": null, "code_iso": null, "code_glottolog": null, "classification_wals": "An.GREATER_CENTRAL_PHILIPPINE", "classification_ethnologue": "Austronesian,Malayo-Polynesian,Philippine,GreaterCentralPhilippine,Palawanic", "classification_glottolog": null, "number_of_speakers": 0, "recently_extinct": false, "long_extinct": true, "year_of_extinction": null, "txt": "PROTO_PALAWAN{An.GREATER_CENTRAL_PHILIPPINE|Austronesian,Malayo-Polynesian,Philippine,GreaterCentralPhilippine,Palawanic@}\n 1    8.67  117.30          -2            \n1 I\t7aku //\n2 you\tka //\n3 we\tkami //\n11 one\t7isaq, 73saq //\n12 two\tdua //\n18 person\tta7u //\n19 fish\ts3da7 //\n21 dog\t7id3N //\n22 louse\tkutu //\n23 tree\tkayu //\n25 leaf\tda7un //\n28 skin\tkubal //\n30 blood\tdugu7 //\n31 bone\ttu7laN //\n39 ear\ttaliNa //\n40 eye\tmata //\n41 nose\t7aruN, 7aduN //\n43 tooth\tnip3n //\n44 tongue\tdila7 //\n48 hand\tlima, 7alima //\n53 liver\t7atay //\n54 drink\t7inum //\n57 see\tl3t3g //\n58 hear\teNeg, deNeg, neNeg //\n61 die\tpatay //\n72 sun\t7aldaw //\n74 star\tbitu73n //\n75 water\tdanum //\n77 stone\tbatu //\n82 fire\t7apuy //\n85 path\tdalan //\n86 mountain\tbukid //\n92 night\tgebi7i //\n96 new\tba7gu //\n100 name\tNaran //", "wals_genus": "GREATER_CENTRAL_PHILIPPINE", "wals_family": "An", "ethnologue_family": "Austronesian", "glottolog_family": null, "jsondata": {}, "id": "PROTO_PALAWAN", "name": "Proto Palawan", "description": null, "markup_description": null, "latitude": 8.67, "longitude": 117.3}