{"pk": 6084, "wordlist_pk": 6084, "code_wals": null, "code_iso": "tbk", "code_glottolog": "cala1258", "classification_wals": "An.GREATER_CENTRAL_PHILIPPINE", "classification_ethnologue": "Austronesian,Malayo-Polynesian,Kalamian", "classification_glottolog": "Austronesian,Malayo-Polynesian,Kalamian", "number_of_speakers": 10000, "recently_extinct": false, "long_extinct": false, "year_of_extinction": null, "txt": "TAGBANWA_KALAMIAN{An.GREATER_CENTRAL_PHILIPPINE|Austronesian,Malayo-Polynesian,Kalamian@Austronesian,Malayo-Polynesian,Kalamian}\n 1   12.00  120.00       10000         tbk\n1 I\tyuu //\n2 you\tyawa //\n3 we\tita //\n11 one\ttasa7 //\n12 two\tdurua7 //\n18 person\ttau7 //\n19 fish\tian //\n21 dog\tkiru7 //\n22 louse\ttut7 //\n23 tree\tayu7 //\n25 leaf\tk3lad //\n28 skin\tulit //\n30 blood\tdugu7 //\n31 bone\tduli7 //\n39 ear\ttaliNa7 //\n40 eye\tmata7 //\n41 nose\turuN //\n44 tongue\tdilak //\n47 knee\ttuud //\n48 hand\tkalima7 //\n51 breast\tsusu7 //\n53 liver\tkandas //\n54 drink\tin3m //\n57 see\tita7 //\n58 hear\td3N3l //\n74 star\tbitukun //\n75 water\twai7 //\n77 stone\tbatu7 //\n82 fire\tapuy //\n85 path\tdalan //\n86 mountain\tbukid //\n92 night\tlabii //\n95 full\tpunuk //\n96 new\tbaklu7 //\n100 name\taran //", "wals_genus": "GREATER_CENTRAL_PHILIPPINE", "wals_family": "An", "ethnologue_family": "Austronesian", "glottolog_family": "Austronesian", "jsondata": {}, "id": "TAGBANWA_KALAMIAN", "name": "Tagbanwa Kalamian", "description": null, "markup_description": null, "latitude": 12.0, "longitude": 120.0}